Metadata-Version: 2.4
Name: time-server-mcp
Version: 0.1.1
Summary: A time server implementation using MCP (Model Context Protocol)
Author-email: PCccc <2670891864@qq.com>
Classifier: Programming Language :: Python :: 3
Classifier: License :: OSI Approved :: MIT License
Classifier: Operating System :: OS Independent
Requires-Python: >=3.7
Requires-Dist: pytz
Requires-Dist: mcp
